[
  {
    "verse_id": 6208,
    "words": "قُلْ:",
    "grammar": "فعل أمر مبني على السكون وحذفت الواو لالتقاء الساكنين والفاعل ضمير مستتر فيه وجوبا تقديره أنت.",
    "name_arabic": "الكافرون",
    "chapter_id": 109,
    "text_uthmani": "قُلْ يَا أَيُّهَا الْكَافِرُونَ",
    "verse_number": 1
  },
  {
    "verse_id": 6208,
    "words": "يا أَيُّهَا الْكافِرُونَ:",
    "grammar": "حرف نداء. أي: منادى مبني على الضم في محل نصب و «ها» زائدة للتنبيه. الكافرون: صفة- نعت- لأي مرفوعة مثلها على اللفظ وعلامة رفعها الواو لأنها جمع مذكر سالم والنون عوض من التنوين والحركة في المفرد.",
    "name_arabic": "الكافرون",
    "chapter_id": 109,
    "text_uthmani": "قُلْ يَا أَيُّهَا الْكَافِرُونَ",
    "verse_number": 1
  },
  {
    "verse_id": 6209,
    "words": "لا أَعْبُدُ ما:",
    "grammar": "نافية لا عمل لها. أعبد: فعل مضارع مرفوع بالضمة والفاعل ضمير مستتر فيه وجوبا تقديره أنا. ما: اسم موصول بمعنى «الذي» مبني على السكون في محل نصب مفعول به. والجملة في محل نصب مفعول «قل».",
    "name_arabic": "الكافرون",
    "chapter_id": 109,
    "text_uthmani": "لَا أَعْبُدُ مَا تَعْبُدُونَ",
    "verse_number": 2
  },
  {
    "verse_id": 6209,
    "words": "تَعْبُدُونَ:",
    "grammar": "فعل مضارع مرفوع بثبوت النون والواو ضمير متصل في محل رفع فاعل. والجملة: صلة الموصول لا محل لها من الاعراب. والعائد- الراجع- الى الموصول ضمير محذوف منصوب المحل لأنه مفعول به التقدير تعبدونه.",
    "name_arabic": "الكافرون",
    "chapter_id": 109,
    "text_uthmani": "لَا أَعْبُدُ مَا تَعْبُدُونَ",
    "verse_number": 2
  },
  {
    "verse_id": 6210,
    "words": "وَلا أَنْتُمْ:",
    "grammar": "الواو عاطفة. لا: نافية لا عمل لها. أنتم: ضمير رفع منفصل مبني على السكون في محل رفع مبتدأ.",
    "name_arabic": "الكافرون",
    "chapter_id": 109,
    "text_uthmani": "وَلَا أَنتُمْ عَابِدُونَ مَا أَعْبُدُ",
    "verse_number": 3
  },
  {
    "verse_id": 6210,
    "words": "عابِدُونَ ما أَعْبُدُ:",
    "grammar": "خبر «أنتم» مرفوع بالواو لأنه جمع مذكر سالم والنون عوض من التنوين والحركة في المفرد. ما أعبد: تعرب اعراب «ما تَعْبُدُونَ» وعلامة رفع الفعل الضمة وفاعله ضمير مستتر فيه وجوبا تقديره أنا و «ما» يعود على الله ويجوز أن تكون «ما» مصدرية فيكون التقدير لا أعبد عبادتكم ولا تعبدون عبادتي. وما: اسم موصول في محل نصب مفعول اسم الفاعل «عابدون» الذي تعمل عمل فعله.",
    "name_arabic": "الكافرون",
    "chapter_id": 109,
    "text_uthmani": "وَلَا أَنتُمْ عَابِدُونَ مَا أَعْبُدُ",
    "verse_number": 3
  },
  {
    "verse_id": 6211,
    "words": "وَلا أَنا عابِدٌ:",
    "grammar": "أعربت. أنا: ضمير رفع منفصل مبني على السكون في محل رفع مبتدأ. عابد: خبر «أنا» مرفوع بالضمة.",
    "name_arabic": "الكافرون",
    "chapter_id": 109,
    "text_uthmani": "وَلَا أَنَا عَابِدٌ مَّا عَبَدتُّمْ",
    "verse_number": 4
  },
  {
    "verse_id": 6211,
    "words": "ما عَبَدْتُّمْ:",
    "grammar": "تعرب اعراب «ما تَعْبُدُونَ» «عبدتم» فعل ماض مبني على السكون لاتصاله بضمير الرفع المتحرك. والتاء ضمير متصل- ضمير المخاطبين- مبني على الضم في محل رفع فاعل والميم علامة جمع الذكور.",
    "name_arabic": "الكافرون",
    "chapter_id": 109,
    "text_uthmani": "وَلَا أَنَا عَابِدٌ مَّا عَبَدتُّمْ",
    "verse_number": 4
  },
  {
    "verse_id": 6212,
    "words": "وَلا أَنْتُمْ عابِدُونَ ما أَعْبُدُ",
    "grammar": "تعرب الآية اعراب الآية الكريمة الثالثة وهي مكررة.",
    "name_arabic": "الكافرون",
    "chapter_id": 109,
    "text_uthmani": "وَلَا أَنتُمْ عَابِدُونَ مَا أَعْبُدُ",
    "verse_number": 5
  },
  {
    "verse_id": 6213,
    "words": "لَكُمْ دِينُكُمْ:",
    "grammar": "جار ومجرور متعلق بخبر مقدم والميم علامة جمع الذكور.دينكم: مبتدأ مؤخر مرفوع بالضمة. والكاف ضمير متصل في محل جر بالاضافة. والميم علامة جمع الذكور.",
    "name_arabic": "الكافرون",
    "chapter_id": 109,
    "text_uthmani": "لَكُمْ دِينُكُمْ وَلِيَ دِينِ",
    "verse_number": 6
  },
  {
    "verse_id": 6213,
    "words": "وَلِيَ دِينِ:",
    "grammar": "معطوفة بالواو على «لَكُمْ دِينُكُمْ» وتعرب اعرابها والياء المحذوفة ضمير متصل في محل جر بالاضافة والكسرة دالة عليها.",
    "name_arabic": "الكافرون",
    "chapter_id": 109,
    "text_uthmani": "لَكُمْ دِينُكُمْ وَلِيَ دِينِ",
    "verse_number": 6
  }
]